setup.cfg
setup.py
coursera_notes_merge/__init__.py
coursera_notes_merge/cli.py
coursera_notes_merge.egg-info/PKG-INFO
coursera_notes_merge.egg-info/SOURCES.txt
coursera_notes_merge.egg-info/dependency_links.txt
coursera_notes_merge.egg-info/entry_points.txt
coursera_notes_merge.egg-info/not-zip-safe
coursera_notes_merge.egg-info/requires.txt
coursera_notes_merge.egg-info/top_level.txt